[
  { "name": "Andorra", "code": "ad.svg" },
  { "name": "United Arab Emirates", "code": "ae.svg" },
  { "name": "Afghanistan", "code": "af.svg" },
  { "name": "Antigua and Barbuda", "code": "ag.svg" },
  { "name": "Anguilla", "code": "ai.svg" },
  { "name": "Albania", "code": "al.svg" },
  { "name": "Armenia", "code": "am.svg" },
  { "name": "Angola", "code": "ao.svg" },
  { "name": "Antarctica", "code": "aq.svg" },
  { "name": "Argentina", "code": "ar.svg" },
  { "name": "American Samoa", "code": "as.svg" },
  { "name": "Austria", "code": "at.svg" },
  { "name": "Australia", "code": "au.svg" },
  { "name": "Aruba", "code": "aw.svg" },
  { "name": "Åland Islands", "code": "ax.svg" },
  { "name": "Azerbaijan", "code": "az.svg" },
  { "name": "Bosnia and Herzegovina", "code": "ba.svg" },
  { "name": "Barbados", "code": "bb.svg" },
  { "name": "Bangladesh", "code": "bd.svg" },
  { "name": "Belgium", "code": "be.svg" },
  { "name": "Burkina Faso", "code": "bf.svg" },
  { "name": "Bulgaria", "code": "bg.svg" },
  { "name": "Bahrain", "code": "bh.svg" },
  { "name": "Burundi", "code": "bi.svg" },
  { "name": "Benin", "code": "bj.svg" },
  { "name": "Saint Barthélemy", "code": "bl.svg" },
  { "name": "Bermuda", "code": "bm.svg" },
  { "name": "Brunei Darussalam", "code": "bn.svg" },
  { "name": "Bolivia, Plurinational State of", "code": "bo.svg" },
  { "name": "Caribbean Netherlands", "code": "bq.svg" },
  { "name": "Brazil", "code": "br.svg" },
  { "name": "Bahamas", "code": "bs.svg" },
  { "name": "Bhutan", "code": "bt.svg" },
  { "name": "Bouvet Island", "code": "bv.svg" },
  { "name": "Botswana", "code": "bw.svg" },
  { "name": "Belarus", "code": "by.svg" },
  { "name": "Belize", "code": "bz.svg" },
  { "name": "Canada", "code": "ca.svg" },
  { "name": "Cocos (Keeling) Islands", "code": "cc.svg" },
  { "name": "Congo, the Democratic Republic of the", "code": "cd.svg" },
  { "name": "Central African Republic", "code": "cf.svg" },
  { "name": "Republic of the Congo", "code": "cg.svg" },
  { "name": "Switzerland", "code": "ch.svg" },
  { "name": "Côte d'Ivoire", "code": "ci.svg" },
  { "name": "Cook Islands", "code": "ck.svg" },
  { "name": "Chile", "code": "cl.svg" },
  { "name": "Cameroon", "code": "cm.svg" },
  { "name": "China (People's Republic of China)", "code": "cn.svg" },
  { "name": "Colombia", "code": "co.svg" },
  { "name": "Costa Rica", "code": "cr.svg" },
  { "name": "Cuba", "code": "cu.svg" },
  { "name": "Cape Verde", "code": "cv.svg" },
  { "name": "Curaçao", "code": "cw.svg" },
  { "name": "Christmas Island", "code": "cx.svg" },
  { "name": "Cyprus", "code": "cy.svg" },
  { "name": "Czech Republic", "code": "cz.svg" },
  { "name": "Germany", "code": "de.svg" },
  { "name": "Djibouti", "code": "dj.svg" },
  { "name": "Denmark", "code": "dk.svg" },
  { "name": "Dominica", "code": "dm.svg" },
  { "name": "Dominican Republic", "code": "do.svg" },
  { "name": "Algeria", "code": "dz.svg" },
  { "name": "Ecuador", "code": "ec.svg" },
  { "name": "Estonia", "code": "ee.svg" },
  { "name": "Egypt", "code": "eg.svg" },
  { "name": "Western Sahara", "code": "eh.svg" },
  { "name": "Eritrea", "code": "er.svg" },
  { "name": "Spain", "code": "es.svg" },
  { "name": "Ethiopia", "code": "et.svg" },
  { "name": "Europe", "code": "eu.svg" },
  { "name": "Finland", "code": "fi.svg" },
  { "name": "Fiji", "code": "fj.svg" },
  { "name": "Falkland Islands (Malvinas)", "code": "fk.svg" },
  { "name": "Micronesia, Federated States of", "code": "fm.svg" },
  { "name": "Faroe Islands", "code": "fo.svg" },
  { "name": "France", "code": "fr.svg" },
  { "name": "Gabon", "code": "ga.svg" },
  { "name": "England", "code": "ng.svg" },
  { "name": "Northern Ireland", "code": "ir.svg" },
  { "name": "Scotland", "code": "ct.svg" },
  { "name": "Wales", "code": "ls.svg" },
  { "name": "United Kingdom", "code": "gb.svg" },
  { "name": "Grenada", "code": "gd.svg" },
  { "name": "Georgia", "code": "ge.svg" },
  { "name": "French Guiana", "code": "gf.svg" },
  { "name": "Guernsey", "code": "gg.svg" },
  { "name": "Ghana", "code": "gh.svg" },
  { "name": "Gibraltar", "code": "gi.svg" },
  { "name": "Greenland", "code": "gl.svg" },
  { "name": "Gambia", "code": "gm.svg" },
  { "name": "Guinea", "code": "gn.svg" },
  { "name": "Guadeloupe", "code": "gp.svg" },
  { "name": "Equatorial Guinea", "code": "gq.svg" },
  { "name": "Greece", "code": "gr.svg" },
  { "name": "South Georgia and the South Sandwich Islands", "code": "gs.svg" },
  { "name": "Guatemala", "code": "gt.svg" },
  { "name": "Guam", "code": "gu.svg" },
  { "name": "Guinea-Bissau", "code": "gw.svg" },
  { "name": "Guyana", "code": "gy.svg" },
  { "name": "Hong Kong", "code": "hk.svg" },
  { "name": "Heard Island and McDonald Islands", "code": "hm.svg" },
  { "name": "Honduras", "code": "hn.svg" },
  { "name": "Croatia", "code": "hr.svg" },
  { "name": "Haiti", "code": "ht.svg" },
  { "name": "Hungary", "code": "hu.svg" },
  { "name": "Indonesia", "code": "id.svg" },
  { "name": "Ireland", "code": "ie.svg" },
  { "name": "Israel", "code": "il.svg" },
  { "name": "Isle of Man", "code": "im.svg" },
  { "name": "India", "code": "in.svg" },
  { "name": "British Indian Ocean Territory", "code": "io.svg" },
  { "name": "Iraq", "code": "iq.svg" },
  { "name": "Iran, Islamic Republic of", "code": "ir.svg" },
  { "name": "Iceland", "code": "is.svg" },
  { "name": "Italy", "code": "it.svg" },
  { "name": "Jersey", "code": "je.svg" },
  { "name": "Jamaica", "code": "jm.svg" },
  { "name": "Jordan", "code": "jo.svg" },
  { "name": "Japan", "code": "jp.svg" },
  { "name": "Kenya", "code": "ke.svg" },
  { "name": "Kyrgyzstan", "code": "kg.svg" },
  { "name": "Cambodia", "code": "kh.svg" },
  { "name": "Kiribati", "code": "ki.svg" },
  { "name": "Comoros", "code": "km.svg" },
  { "name": "Saint Kitts and Nevis", "code": "kn.svg" },
  { "name": "Korea, Democratic People's Republic of", "code": "kp.svg" },
  { "name": "Korea, Republic of", "code": "kr.svg" },
  { "name": "Kuwait", "code": "kw.svg" },
  { "name": "Cayman Islands", "code": "ky.svg" },
  { "name": "Kazakhstan", "code": "kz.svg" },
  { "name": "Laos (Lao People's Democratic Republic)", "code": "la.svg" },
  { "name": "Lebanon", "code": "lb.svg" },
  { "name": "Saint Lucia", "code": "lc.svg" },
  { "name": "Liechtenstein", "code": "li.svg" },
  { "name": "Sri Lanka", "code": "lk.svg" },
  { "name": "Liberia", "code": "lr.svg" },
  { "name": "Lesotho", "code": "ls.svg" },
  { "name": "Lithuania", "code": "lt.svg" },
  { "name": "Luxembourg", "code": "lu.svg" },
  { "name": "Latvia", "code": "lv.svg" },
  { "name": "Libya", "code": "ly.svg" },
  { "name": "Morocco", "code": "ma.svg" },
  { "name": "Monaco", "code": "mc.svg" },
  { "name": "Moldova, Republic of", "code": "md.svg" },
  { "name": "Montenegro", "code": "me.svg" },
  { "name": "Saint Martin", "code": "mf.svg" },
  { "name": "Madagascar", "code": "mg.svg" },
  { "name": "Marshall Islands", "code": "mh.svg" },
  { "name": "North Macedonia", "code": "mk.svg" },
  { "name": "Mali", "code": "ml.svg" },
  { "name": "Myanmar", "code": "mm.svg" },
  { "name": "Mongolia", "code": "mn.svg" },
  { "name": "Macao", "code": "mo.svg" },
  { "name": "Northern Mariana Islands", "code": "mp.svg" },
  { "name": "Martinique", "code": "mq.svg" },
  { "name": "Mauritania", "code": "mr.svg" },
  { "name": "Montserrat", "code": "ms.svg" },
  { "name": "Malta", "code": "mt.svg" },
  { "name": "Mauritius", "code": "mu.svg" },
  { "name": "Maldives", "code": "mv.svg" },
  { "name": "Malawi", "code": "mw.svg" },
  { "name": "Mexico", "code": "mx.svg" },
  { "name": "Malaysia", "code": "my.svg" },
  { "name": "Mozambique", "code": "mz.svg" },
  { "name": "Namibia", "code": "na.svg" },
  { "name": "New Caledonia", "code": "nc.svg" },
  { "name": "Niger", "code": "ne.svg" },
  { "name": "Norfolk Island", "code": "nf.svg" },
  { "name": "Nigeria", "code": "ng.svg" },
  { "name": "Nicaragua", "code": "ni.svg" },
  { "name": "Netherlands", "code": "nl.svg" },
  { "name": "Norway", "code": "no.svg" },
  { "name": "Nepal", "code": "np.svg" },
  { "name": "Nauru", "code": "nr.svg" },
  { "name": "Niue", "code": "nu.svg" },
  { "name": "New Zealand", "code": "nz.svg" },
  { "name": "Oman", "code": "om.svg" },
  { "name": "Panama", "code": "pa.svg" },
  { "name": "Peru", "code": "pe.svg" },
  { "name": "French Polynesia", "code": "pf.svg" },
  { "name": "Papua New Guinea", "code": "pg.svg" },
  { "name": "Philippines", "code": "ph.svg" },
  { "name": "Pakistan", "code": "pk.svg" },
  { "name": "Poland", "code": "pl.svg" },
  { "name": "Saint Pierre and Miquelon", "code": "pm.svg" },
  { "name": "Pitcairn", "code": "pn.svg" },
  { "name": "Puerto Rico", "code": "pr.svg" },
  { "name": "Palestine", "code": "ps.svg" },
  { "name": "Portugal", "code": "pt.svg" },
  { "name": "Palau", "code": "pw.svg" },
  { "name": "Paraguay", "code": "py.svg" },
  { "name": "Qatar", "code": "qa.svg" },
  { "name": "Réunion", "code": "re.svg" },
  { "name": "Romania", "code": "ro.svg" },
  { "name": "Serbia", "code": "rs.svg" },
  { "name": "Russian Federation", "code": "ru.svg" },
  { "name": "Rwanda", "code": "rw.svg" },
  { "name": "Saudi Arabia", "code": "sa.svg" },
  { "name": "Solomon Islands", "code": "sb.svg" },
  { "name": "Seychelles", "code": "sc.svg" },
  { "name": "Sudan", "code": "sd.svg" },
  { "name": "Sweden", "code": "se.svg" },
  { "name": "Singapore", "code": "sg.svg" },
  { "name": "Saint Helena, Ascension and Tristan da Cunha", "code": "sh.svg" },
  { "name": "Slovenia", "code": "si.svg" },
  { "name": "Svalbard and Jan Mayen Islands", "code": "sj.svg" },
  { "name": "Slovakia", "code": "sk.svg" },
  { "name": "Sierra Leone", "code": "sl.svg" },
  { "name": "San Marino", "code": "sm.svg" },
  { "name": "Senegal", "code": "sn.svg" },
  { "name": "Somalia", "code": "so.svg" },
  { "name": "Suriname", "code": "sr.svg" },
  { "name": "South Sudan", "code": "ss.svg" },
  { "name": "Sao Tome and Principe", "code": "st.svg" },
  { "name": "El Salvador", "code": "sv.svg" },
  { "name": "Sint Maarten (Dutch part)", "code": "sx.svg" },
  { "name": "Syrian Arab Republic", "code": "sy.svg" },
  { "name": "Swaziland", "code": "sz.svg" },
  { "name": "Turks and Caicos Islands", "code": "tc.svg" },
  { "name": "Chad", "code": "td.svg" },
  { "name": "French Southern Territories", "code": "tf.svg" },
  { "name": "Togo", "code": "tg.svg" },
  { "name": "Thailand", "code": "th.svg" },
  { "name": "Tajikistan", "code": "tj.svg" },
  { "name": "Tokelau", "code": "tk.svg" },
  { "name": "Timor-Leste", "code": "tl.svg" },
  { "name": "Turkmenistan", "code": "tm.svg" },
  { "name": "Tunisia", "code": "tn.svg" },
  { "name": "Tonga", "code": "to.svg" },
  { "name": "Turkey", "code": "tr.svg" },
  { "name": "Trinidad and Tobago", "code": "tt.svg" },
  { "name": "Tuvalu", "code": "tv.svg" },
  { "name": "Taiwan (Republic of China)", "code": "tw.svg" },
  { "name": "Tanzania, United Republic of", "code": "tz.svg" },
  { "name": "Ukraine", "code": "ua.svg" },
  { "name": "Uganda", "code": "ug.svg" },
  { "name": "US Minor Outlying Islands", "code": "um.svg" },
  { "name": "United States", "code": "us.svg" },
  { "name": "Uruguay", "code": "uy.svg" },
  { "name": "Uzbekistan", "code": "uz.svg" },
  { "name": "Holy See (Vatican City State)", "code": "va.svg" },
  { "name": "Saint Vincent and the Grenadines", "code": "vc.svg" },
  { "name": "Venezuela, Bolivarian Republic of", "code": "ve.svg" },
  { "name": "Virgin Islands, British", "code": "vg.svg" },
  { "name": "Virgin Islands, U.S.", "code": "vi.svg" },
  { "name": "Vietnam", "code": "vn.svg" },
  { "name": "Vanuatu", "code": "vu.svg" },
  { "name": "Wallis and Futuna Islands", "code": "wf.svg" },
  { "name": "Samoa", "code": "ws.svg" },
  { "name": "Kosovo", "code": "xk.svg" },
  { "name": "Yemen", "code": "ye.svg" },
  { "name": "Mayotte", "code": "yt.svg" },
  { "name": "South Africa", "code": "za.svg" },
  { "name": "Zambia", "code": "zm.svg" },
  { "name": "Zimbabwe", "code": "zw.svg" }
  ]
  